streamlit_link_button_extended/__init__.py
streamlit_link_button_extended/frontend/index.html
streamlit_link_button_extended/frontend/main.js
streamlit_link_button_extended/frontend/streamlit-component-lib.js
streamlit_link_button_extended/frontend/style.css
streamlit_link_button_extended-0.2.3.dist-info/LICENSE
streamlit_link_button_extended-0.2.3.dist-info/METADATA
streamlit_link_button_extended-0.2.3.dist-info/WHEEL
streamlit_link_button_extended-0.2.3.dist-info/top_level.txt
streamlit_link_button_extended-0.2.3.dist-info/RECORD
