Metadata-Version: 2.1
Name: streamlit-link-button-extended
Version: 0.2.3
Summary: Streamlit Component that allows the developer to track when it's been clicked
Author: Alexander Rogiers
Author-email: alexander.rogiers@ugent.be
Requires-Python: >=3.7
License-File: LICENSE
Requires-Dist: streamlit >=1.2
Requires-Dist: jinja2
